homing_search/__init__.py
homing_search/data.py
homing_search/search.py
homing_search/utils.py
homing_search_keras-0.0.6.dist-info/LICENSE.txt
homing_search_keras-0.0.6.dist-info/METADATA
homing_search_keras-0.0.6.dist-info/WHEEL
homing_search_keras-0.0.6.dist-info/top_level.txt
homing_search_keras-0.0.6.dist-info/RECORD
