Metadata-Version: 2.1
Name: homing-search-keras
Version: 0.0.6
Summary: Smart hyperparameter optimization in Python
Home-page: https://github.com/talkingtoaj/homing_search
Author: Andrew de Jonge
Author-email: talkingtoaj@hotmail.com
License: UNKNOWN
Platform: UNKNOWN
Classifier: Programming Language :: Python :: 3
Classifier: Development Status :: 3 - Alpha
Classifier: License :: OSI Approved :: BSD License
Classifier: Intended Audience :: Developers
Classifier: Operating System :: OS Independent
Classifier: Topic :: Scientific/Engineering :: Artificial Intelligence
Requires-Python: >=3.6
